[
  {
    "title": "Hangi içeceği daha çok seversin?",
    "desc": "Çay mı, kahve mi, gazoz mu? Oyunu ver; +10 puanı kap!",
    "image": "assets/og-banner.jpg",
    "link": "anketler/anket-1.html"
  },
  {
    "title": "En lezzetli Türk tatlısı hangisi?",
    "desc": "Baklava mı, künefe mi, sütlaç mı? Oy ver; +10 puan kazan!",
    "image": "assets/og-banner.jpg",
    "link": "anketler/anket-2.html"
  }
{
  "title": "En sevdiğin mevsim hangisi?",
  "desc": "İlkbahar mı, yaz mı, sonbahar mı, kış mı? Oy ver; +10 puan kazan!",
  "image": "assets/og-banner.jpg",
  "link": "anketler/anket-3.html"
}
]
  
